iso_4217/__init__.py
iso_4217/currency.py
iso_4217/lists.py
iso_4217/pint.py
iso_4217/data/list-one.xml
iso_4217/data/list-three.xml
iso_4217-0.8.260101.dist-info/licenses/LICENSE
iso_4217-0.8.260101.dist-info/METADATA
iso_4217-0.8.260101.dist-info/WHEEL
iso_4217-0.8.260101.dist-info/top_level.txt
iso_4217-0.8.260101.dist-info/zip-safe
iso_4217-0.8.260101.dist-info/RECORD
