Metadata-Version: 2.4
Name: iso_4217
Version: 0.8.260101
Summary: ISO 4217 currency code library
Author: Igor Kozyrenko
Author-email: igor@ikseek.com
License: MIT
Classifier: Intended Audience :: Financial and Insurance Industry
Classifier: Operating System :: OS Independent
Classifier: Topic :: Software Development :: Libraries
Requires-Python: <4,>=3.8
License-File: LICENSE
Provides-Extra: pint
Requires-Dist: Pint>=0.16; extra == "pint"
Provides-Extra: test
Requires-Dist: pytest; extra == "test"
Dynamic: license-file
